jinja_autodoc/__init__.py
jinja_autodoc/autotemplate.py
jinja_autodoc/domain.py
jinja_autodoc-0.1.4.dist-info/METADATA
jinja_autodoc-0.1.4.dist-info/WHEEL
jinja_autodoc-0.1.4.dist-info/licenses/LICENSE
jinja_autodoc-0.1.4.dist-info/RECORD
