Metadata-Version: 2.4
Name: jinja_autodoc
Version: 0.1.4
Summary: Jinja domain for jinja templates
Project-URL: documentation, https://jinja-autodoc.readthedocs.io
Project-URL: repository, https://github.com/sphinx-contrib/jinja-autodoc
Author-email: Jaka Hudoklin <jakahudoklin@gmail.com>
Maintainer-email: Éloi Rivard <eloi.rivard@nubla.fr>
License: BSD License
License-File: LICENSE
Classifier: Development Status :: 4 - Beta
Classifier: Environment :: Console
Classifier: Environment :: Web Environment
Classifier: Intended Audience :: Developers
Classifier: License :: OSI Approved :: BSD License
Classifier: Operating System :: OS Independent
Classifier: Programming Language :: Python
Classifier: Topic :: Documentation
Classifier: Topic :: Utilities
Requires-Python: >=3.9
Requires-Dist: jinja2>=3.0.0
Requires-Dist: sphinx>=7.4.0
